{"pairid": "200", "first": {"dbid": "6305", "project": "deeplearning4j", "file": "nd4j/nd4j-backends/nd4j-api-parent/nd4j-api/src/main/java/org/nd4j/autodiff/samediff/SameDiff.java", "method": "SameDiff.sru(SRUConfiguration)"}, "second": {"dbid": "36436", "project": "openjdk11", "file": "src/jdk.javadoc/share/classes/jdk/javadoc/internal/doclets/formats/html/ClassUseWriter.java", "method": "ClassUseWriter.generate(HtmlConfiguration, ClassTree)"}, "goals": [{"rating": 0, "confidence": 2}, {"rating": -1, "confidence": -1}, {"rating": 0, "confidence": 2}, {"rating": -1, "confidence": -1}, {"rating": -1, "confidence": -1}, {"rating": -1, "confidence": -1}, {"rating": -1, "confidence": -1}, {"rating": 0, "confidence": 2}], "operations": [{"rating": 0, "confidence": 2}, {"rating": -1, "confidence": -1}, {"rating": 0, "confidence": 2}, {"rating": -1, "confidence": -1}, {"rating": -1, "confidence": -1}, {"rating": -1, "confidence": -1}, {"rating": -1, "confidence": -1}, {"rating": 0, "confidence": 2}], "effects": [{"rating": 0, "confidence": 2}, {"rating": -1, "confidence": -1}, {"rating": 0, "confidence": 2}, {"rating": -1, "confidence": -1}, {"rating": -1, "confidence": -1}, {"rating": -1, "confidence": -1}, {"rating": -1, "confidence": -1}, {"rating": 0, "confidence": 2}]}