{"pairid": "771", "first": {"dbid": "11882", "project": "eclipse.jdt.core", "file": "org.eclipse.jdt.core/compiler/org/eclipse/jdt/internal/compiler/ClassFile.java", "method": "ClassFile.generateCodeAttributeHeader()"}, "second": {"dbid": "50332", "project": "openjdk11", "file": "src/java.xml/share/classes/com/sun/org/apache/xerces/internal/dom/AttrImpl.java", "method": "AttrImpl.getNodeName()"}, "goals": [{"rating": 0, "confidence": 2}, {"rating": -1, "confidence": -1}, {"rating": -1, "confidence": -1}, {"rating": -1, "confidence": -1}, {"rating": -1, "confidence": -1}, {"rating": -1, "confidence": -1}, {"rating": 0, "confidence": 2}, {"rating": 0, "confidence": 2}], "operations": [{"rating": 0, "confidence": 2}, {"rating": -1, "confidence": -1}, {"rating": -1, "confidence": -1}, {"rating": -1, "confidence": -1}, {"rating": -1, "confidence": -1}, {"rating": -1, "confidence": -1}, {"rating": 0, "confidence": 2}, {"rating": 0, "confidence": 2}], "effects": [{"rating": 0, "confidence": 2}, {"rating": -1, "confidence": -1}, {"rating": -1, "confidence": -1}, {"rating": -1, "confidence": -1}, {"rating": -1, "confidence": -1}, {"rating": -1, "confidence": -1}, {"rating": 0, "confidence": 2}, {"rating": 0, "confidence": 2}]}