{"pairid": "846", "first": {"dbid": "15086", "project": "freemind", "file": "freemind/de/foltin/StringEncoder.java", "method": "StringEncoder.decode(String)"}, "second": {"dbid": "22394", "project": "openjdk11", "file": "test/jdk/sanity/client/lib/jemmy/src/org/netbeans/jemmy/operators/Operator.java", "method": "Operator.unlockAndThrow(Exception)"}, "goals": [{"rating": -1, "confidence": -1}, {"rating": -1, "confidence": -1}, {"rating": 0, "confidence": 2}, {"rating": 0, "confidence": 2}, {"rating": -1, "confidence": -1}, {"rating": -1, "confidence": -1}, {"rating": -1, "confidence": -1}, {"rating": 0, "confidence": 2}], "operations": [{"rating": -1, "confidence": -1}, {"rating": -1, "confidence": -1}, {"rating": 0, "confidence": 2}, {"rating": 0, "confidence": 2}, {"rating": -1, "confidence": -1}, {"rating": -1, "confidence": -1}, {"rating": -1, "confidence": -1}, {"rating": 0, "confidence": 2}], "effects": [{"rating": -1, "confidence": -1}, {"rating": -1, "confidence": -1}, {"rating": 0, "confidence": 2}, {"rating": 0, "confidence": 2}, {"rating": -1, "confidence": -1}, {"rating": -1, "confidence": -1}, {"rating": -1, "confidence": -1}, {"rating": 0, "confidence": 2}]}