{"pairid": "470", "first": {"dbid": "18475", "project": "guava", "file": "guava/src/com/google/common/base/CaseFormat.java", "method": "CaseFormat.convert(CaseFormat, String)"}, "second": {"dbid": "42991", "project": "openjdk11", "file": "src/java.desktop/share/classes/javax/swing/table/DefaultTableCellRenderer.java", "method": "DefaultTableCellRenderer.isOpaque()"}, "goals": [{"rating": -1, "confidence": -1}, {"rating": 0, "confidence": 2}, {"rating": -1, "confidence": -1}, {"rating": -1, "confidence": -1}, {"rating": -1, "confidence": -1}, {"rating": -1, "confidence": -1}, {"rating": 0, "confidence": 2}, {"rating": 0, "confidence": 2}], "operations": [{"rating": -1, "confidence": -1}, {"rating": 0, "confidence": 2}, {"rating": -1, "confidence": -1}, {"rating": -1, "confidence": -1}, {"rating": -1, "confidence": -1}, {"rating": -1, "confidence": -1}, {"rating": 0, "confidence": 2}, {"rating": 0, "confidence": 2}], "effects": [{"rating": -1, "confidence": -1}, {"rating": 0, "confidence": 2}, {"rating": -1, "confidence": -1}, {"rating": -1, "confidence": -1}, {"rating": -1, "confidence": -1}, {"rating": -1, "confidence": -1}, {"rating": 0, "confidence": 2}, {"rating": 0, "confidence": 2}]}