{"pairid": "423", "first": {"dbid": "699", "project": "checkstyle", "file": "src/main/java/com/puppycrawl/tools/checkstyle/checks/regexp/RegexpCheck.java", "method": "RegexpCheck.setFormat(Pattern)"}, "second": {"dbid": "30492", "project": "openjdk11", "file": "src/java.base/share/classes/java/text/MergeCollation.java", "method": "MergeCollation.addPattern(String)"}, "goals": [{"rating": -1, "confidence": -1}, {"rating": -1, "confidence": -1}, {"rating": 0, "confidence": 2}, {"rating": -1, "confidence": -1}, {"rating": -1, "confidence": -1}, {"rating": 0, "confidence": 2}, {"rating": -1, "confidence": -1}, {"rating": 0, "confidence": 1}], "operations": [{"rating": -1, "confidence": -1}, {"rating": -1, "confidence": -1}, {"rating": 0, "confidence": 2}, {"rating": -1, "confidence": -1}, {"rating": -1, "confidence": -1}, {"rating": 0, "confidence": 2}, {"rating": -1, "confidence": -1}, {"rating": 0, "confidence": 2}], "effects": [{"rating": -1, "confidence": -1}, {"rating": -1, "confidence": -1}, {"rating": 0, "confidence": 2}, {"rating": -1, "confidence": -1}, {"rating": -1, "confidence": -1}, {"rating": 0, "confidence": 2}, {"rating": -1, "confidence": -1}, {"rating": 0, "confidence": 2}]}