{"pairid": "146", "first": {"dbid": "1409", "project": "commons-collections", "file": "src/main/java/org/apache/commons/collections4/multiset/AbstractMultiSet.java", "method": "AbstractMultiSet.clear()"}, "second": {"dbid": "29317", "project": "openjdk11", "file": "src/java.base/share/classes/java/util/Timer.java", "method": "TaskQueue.clear()"}, "goals": [{"rating": -1, "confidence": -1}, {"rating": -1, "confidence": -1}, {"rating": 2, "confidence": 2}, {"rating": -1, "confidence": -1}, {"rating": -1, "confidence": -1}, {"rating": 2, "confidence": 2}, {"rating": -1, "confidence": -1}, {"rating": 2, "confidence": 2}], "operations": [{"rating": -1, "confidence": -1}, {"rating": -1, "confidence": -1}, {"rating": 1, "confidence": 2}, {"rating": -1, "confidence": -1}, {"rating": -1, "confidence": -1}, {"rating": 1, "confidence": 2}, {"rating": -1, "confidence": -1}, {"rating": 1, "confidence": 2}], "effects": [{"rating": -1, "confidence": -1}, {"rating": -1, "confidence": -1}, {"rating": 1, "confidence": 2}, {"rating": -1, "confidence": -1}, {"rating": -1, "confidence": -1}, {"rating": 1, "confidence": 2}, {"rating": -1, "confidence": -1}, {"rating": 1, "confidence": 2}]}